kedro_sumz/__init__.py
kedro_sumz/extras/__init__.py
kedro_sumz/extras/context/__init__.py
kedro_sumz/extras/datasets/__init__.py
kedro_sumz/extras/datasets/bigquery.py
kedro_sumz/extras/datasets/delta.py
kedro_sumz/extras/datasets/mlflow.py
kedro_sumz/extras/datasets/spark.py
kedro_sumz/extras/datasets/sparkml.py
kedro_sumz/extras/hooks/__init__.py
kedro_sumz/utils/__init__.py
kedro_sumz/utils/mlflow.py
kedro_sumz/utils/scd.py
kedro_sumz_utils-2.1.0.dist-info/licenses/LICENSE.md
kedro_sumz_utils-2.1.0.dist-info/METADATA
kedro_sumz_utils-2.1.0.dist-info/WHEEL
kedro_sumz_utils-2.1.0.dist-info/top_level.txt
kedro_sumz_utils-2.1.0.dist-info/RECORD
