Metadata-Version: 2.4
Name: kedro-sumz-utils
Version: 2.1.0
Summary: Utility functions and kedro datasets for Data projects.
Author-email: Juan Barreto <juan.barreto@sumz.co>
Project-URL: Homepage, https://github.com/SumzCol/data-utils
Project-URL: Bug Tracker, https://github.com/SumzCol/data-utils/issues
Classifier: Programming Language :: Python :: 3
Classifier: Operating System :: OS Independent
Requires-Python: >=3.9
License-File: LICENSE.md
Requires-Dist: kedro>=0.19.0
Requires-Dist: kedro-mlflow>=0.12.0
Dynamic: license-file
